[
	{
		"Language": "C",
		"time": "0",
		"data": [
			{
				"Hardware": "CPU",
				"Metric": "Temperatures",
				"Sensor": "CPU Package",
				"Value": 51.4,
				"measure": "°C"
			},
			{
				"Hardware": "CPU",
				"Metric": "Powers",
				"Sensor": "CPU Package",
				"Value": 6.3,
				"measure": "W"
			},
			{
				"Hardware": "CPU",
				"Metric": "Powers",
				"Sensor": "CPU Cores",
				"Value": 4.1,
				"measure": "W"
			},
			{
				"Hardware": "CPU",
				"Metric": "Load",
				"Sensor": "Memory",
				"Value": 30,
				"measure": "%"
			},
			{
				"Hardware": "CPU",
				"Metric": "Data",
				"Sensor": "Used Memory",
				"Value": 4.8,
				"measure": "GB"
			}
		]
	},
	{
		"Language": "C",
		"time": "1",
		"data": [
			{
				"Hardware": "CPU",
				"Metric": "Temperatures",
				"Sensor": "CPU Package",
				"Value": 57.8,
				"measure": "°C"
			},
			{
				"Hardware": "CPU",
				"Metric": "Powers",
				"Sensor": "CPU Package",
				"Value": 12.5,
				"measure": "W"
			},
			{
				"Hardware": "CPU",
				"Metric": "Powers",
				"Sensor": "CPU Cores",
				"Value": 10.9,
				"measure": "W"
			},
			{
				"Hardware": "CPU",
				"Metric": "Load",
				"Sensor": "Memory",
				"Value": 30.3,
				"measure": "%"
			},
			{
				"Hardware": "CPU",
				"Metric": "Data",
				"Sensor": "Used Memory",
				"Value": 4.8,
				"measure": "GB"
			}
		]
	},
	{
		"Language": "C",
		"time": "2",
		"data": [
			{
				"Hardware": "CPU",
				"Metric": "Temperatures",
				"Sensor": "CPU Package",
				"Value": 61.5,
				"measure": "°C"
			},
			{
				"Hardware": "CPU",
				"Metric": "Powers",
				"Sensor": "CPU Package",
				"Value": 12.7,
				"measure": "W"
			},
			{
				"Hardware": "CPU",
				"Metric": "Powers",
				"Sensor": "CPU Cores",
				"Value": 11.1,
				"measure": "W"
			},
			{
				"Hardware": "CPU",
				"Metric": "Load",
				"Sensor": "Memory",
				"Value": 30.6,
				"measure": "%"
			},
			{
				"Hardware": "CPU",
				"Metric": "Data",
				"Sensor": "Used Memory",
				"Value": 4.9,
				"measure": "GB"
			}
		]
	},
	{
		"Language": "C",
		"time": "3",
		"data": [
			{
				"Hardware": "CPU",
				"Metric": "Temperatures",
				"Sensor": "CPU Package",
				"Value": 64,
				"measure": "°C"
			},
			{
				"Hardware": "CPU",
				"Metric": "Powers",
				"Sensor": "CPU Package",
				"Value": 12.9,
				"measure": "W"
			},
			{
				"Hardware": "CPU",
				"Metric": "Powers",
				"Sensor": "CPU Cores",
				"Value": 11.1,
				"measure": "W"
			},
			{
				"Hardware": "CPU",
				"Metric": "Load",
				"Sensor": "Memory",
				"Value": 30.9,
				"measure": "%"
			},
			{
				"Hardware": "CPU",
				"Metric": "Data",
				"Sensor": "Used Memory",
				"Value": 4.9,
				"measure": "GB"
			}
		]
	},
	{
		"Language": "C",
		"time": "4",
		"data": [
			{
				"Hardware": "CPU",
				"Metric": "Temperatures",
				"Sensor": "CPU Package",
				"Value": 65.5,
				"measure": "°C"
			},
			{
				"Hardware": "CPU",
				"Metric": "Powers",
				"Sensor": "CPU Package",
				"Value": 12.3,
				"measure": "W"
			},
			{
				"Hardware": "CPU",
				"Metric": "Powers",
				"Sensor": "CPU Cores",
				"Value": 10.5,
				"measure": "W"
			},
			{
				"Hardware": "CPU",
				"Metric": "Load",
				"Sensor": "Memory",
				"Value": 31.2,
				"measure": "%"
			},
			{
				"Hardware": "CPU",
				"Metric": "Data",
				"Sensor": "Used Memory",
				"Value": 4.9,
				"measure": "GB"
			}
		]
	},
	{
		"Language": "C",
		"time": "5",
		"data": [
			{
				"Hardware": "CPU",
				"Metric": "Temperatures",
				"Sensor": "CPU Package",
				"Value": 67.4,
				"measure": "°C"
			},
			{
				"Hardware": "CPU",
				"Metric": "Powers",
				"Sensor": "CPU Package",
				"Value": 14.2,
				"measure": "W"
			},
			{
				"Hardware": "CPU",
				"Metric": "Powers",
				"Sensor": "CPU Cores",
				"Value": 12.8,
				"measure": "W"
			},
			{
				"Hardware": "CPU",
				"Metric": "Load",
				"Sensor": "Memory",
				"Value": 31.6,
				"measure": "%"
			},
			{
				"Hardware": "CPU",
				"Metric": "Data",
				"Sensor": "Used Memory",
				"Value": 5,
				"measure": "GB"
			}
		]
	},
	{
		"Language": "C",
		"time": "6",
		"data": [
			{
				"Hardware": "CPU",
				"Metric": "Temperatures",
				"Sensor": "CPU Package",
				"Value": 68.6,
				"measure": "°C"
			},
			{
				"Hardware": "CPU",
				"Metric": "Powers",
				"Sensor": "CPU Package",
				"Value": 15.1,
				"measure": "W"
			},
			{
				"Hardware": "CPU",
				"Metric": "Powers",
				"Sensor": "CPU Cores",
				"Value": 13.9,
				"measure": "W"
			},
			{
				"Hardware": "CPU",
				"Metric": "Load",
				"Sensor": "Memory",
				"Value": 32.3,
				"measure": "%"
			},
			{
				"Hardware": "CPU",
				"Metric": "Data",
				"Sensor": "Used Memory",
				"Value": 5.1,
				"measure": "GB"
			}
		]
	},
	{
		"Language": "C",
		"time": "7",
		"data": [
			{
				"Hardware": "CPU",
				"Metric": "Temperatures",
				"Sensor": "CPU Package",
				"Value": 68.8,
				"measure": "°C"
			},
			{
				"Hardware": "CPU",
				"Metric": "Powers",
				"Sensor": "CPU Package",
				"Value": 12.5,
				"measure": "W"
			},
			{
				"Hardware": "CPU",
				"Metric": "Powers",
				"Sensor": "CPU Cores",
				"Value": 11,
				"measure": "W"
			},
			{
				"Hardware": "CPU",
				"Metric": "Load",
				"Sensor": "Memory",
				"Value": 32.6,
				"measure": "%"
			},
			{
				"Hardware": "CPU",
				"Metric": "Data",
				"Sensor": "Used Memory",
				"Value": 5.2,
				"measure": "GB"
			}
		]
	},
	{
		"Language": "C",
		"time": "8",
		"data": [
			{
				"Hardware": "CPU",
				"Metric": "Temperatures",
				"Sensor": "CPU Package",
				"Value": 68.4,
				"measure": "°C"
			},
			{
				"Hardware": "CPU",
				"Metric": "Powers",
				"Sensor": "CPU Package",
				"Value": 8.2,
				"measure": "W"
			},
			{
				"Hardware": "CPU",
				"Metric": "Powers",
				"Sensor": "CPU Cores",
				"Value": 7.6,
				"measure": "W"
			},
			{
				"Hardware": "CPU",
				"Metric": "Load",
				"Sensor": "Memory",
				"Value": 32.9,
				"measure": "%"
			},
			{
				"Hardware": "CPU",
				"Metric": "Data",
				"Sensor": "Used Memory",
				"Value": 5.2,
				"measure": "GB"
			}
		]
	},
	{
		"Language": "C",
		"time": "9",
		"data": [
			{
				"Hardware": "CPU",
				"Metric": "Temperatures",
				"Sensor": "CPU Package",
				"Value": 67.8,
				"measure": "°C"
			},
			{
				"Hardware": "CPU",
				"Metric": "Powers",
				"Sensor": "CPU Package",
				"Value": 6.7,
				"measure": "W"
			},
			{
				"Hardware": "CPU",
				"Metric": "Powers",
				"Sensor": "CPU Cores",
				"Value": 6.1,
				"measure": "W"
			},
			{
				"Hardware": "CPU",
				"Metric": "Load",
				"Sensor": "Memory",
				"Value": 34.2,
				"measure": "%"
			},
			{
				"Hardware": "CPU",
				"Metric": "Data",
				"Sensor": "Used Memory",
				"Value": 5.4,
				"measure": "GB"
			}
		]
	},
	{
		"Language": "C",
		"time": "10",
		"data": [
			{
				"Hardware": "CPU",
				"Metric": "Temperatures",
				"Sensor": "CPU Package",
				"Value": 67.3,
				"measure": "°C"
			},
			{
				"Hardware": "CPU",
				"Metric": "Powers",
				"Sensor": "CPU Package",
				"Value": 8,
				"measure": "W"
			},
			{
				"Hardware": "CPU",
				"Metric": "Powers",
				"Sensor": "CPU Cores",
				"Value": 7.3,
				"measure": "W"
			},
			{
				"Hardware": "CPU",
				"Metric": "Load",
				"Sensor": "Memory",
				"Value": 32.6,
				"measure": "%"
			},
			{
				"Hardware": "CPU",
				"Metric": "Data",
				"Sensor": "Used Memory",
				"Value": 5.2,
				"measure": "GB"
			}
		]
	},
	{
		"Language": "C",
		"time": "11",
		"data": [
			{
				"Hardware": "CPU",
				"Metric": "Temperatures",
				"Sensor": "CPU Package",
				"Value": 66.8,
				"measure": "°C"
			},
			{
				"Hardware": "CPU",
				"Metric": "Powers",
				"Sensor": "CPU Package",
				"Value": 6.9,
				"measure": "W"
			},
			{
				"Hardware": "CPU",
				"Metric": "Powers",
				"Sensor": "CPU Cores",
				"Value": 6.2,
				"measure": "W"
			},
			{
				"Hardware": "CPU",
				"Metric": "Load",
				"Sensor": "Memory",
				"Value": 33.9,
				"measure": "%"
			},
			{
				"Hardware": "CPU",
				"Metric": "Data",
				"Sensor": "Used Memory",
				"Value": 5.4,
				"measure": "GB"
			}
		]
	},
	{
		"Language": "C",
		"time": "12",
		"data": [
			{
				"Hardware": "CPU",
				"Metric": "Temperatures",
				"Sensor": "CPU Package",
				"Value": 66.3,
				"measure": "°C"
			},
			{
				"Hardware": "CPU",
				"Metric": "Powers",
				"Sensor": "CPU Package",
				"Value": 9,
				"measure": "W"
			},
			{
				"Hardware": "CPU",
				"Metric": "Powers",
				"Sensor": "CPU Cores",
				"Value": 8.6,
				"measure": "W"
			},
			{
				"Hardware": "CPU",
				"Metric": "Load",
				"Sensor": "Memory",
				"Value": 32.5,
				"measure": "%"
			},
			{
				"Hardware": "CPU",
				"Metric": "Data",
				"Sensor": "Used Memory",
				"Value": 5.1,
				"measure": "GB"
			}
		]
	},
	{
		"Language": "C",
		"time": "13",
		"data": [
			{
				"Hardware": "CPU",
				"Metric": "Temperatures",
				"Sensor": "CPU Package",
				"Value": 65.9,
				"measure": "°C"
			},
			{
				"Hardware": "CPU",
				"Metric": "Powers",
				"Sensor": "CPU Package",
				"Value": 7.3,
				"measure": "W"
			},
			{
				"Hardware": "CPU",
				"Metric": "Powers",
				"Sensor": "CPU Cores",
				"Value": 7.2,
				"measure": "W"
			},
			{
				"Hardware": "CPU",
				"Metric": "Load",
				"Sensor": "Memory",
				"Value": 33.3,
				"measure": "%"
			},
			{
				"Hardware": "CPU",
				"Metric": "Data",
				"Sensor": "Used Memory",
				"Value": 5.3,
				"measure": "GB"
			}
		]
	},
	{
		"Language": "C",
		"time": "14",
		"data": [
			{
				"Hardware": "CPU",
				"Metric": "Temperatures",
				"Sensor": "CPU Package",
				"Value": 65.5,
				"measure": "°C"
			},
			{
				"Hardware": "CPU",
				"Metric": "Powers",
				"Sensor": "CPU Package",
				"Value": 8.8,
				"measure": "W"
			},
			{
				"Hardware": "CPU",
				"Metric": "Powers",
				"Sensor": "CPU Cores",
				"Value": 8.5,
				"measure": "W"
			},
			{
				"Hardware": "CPU",
				"Metric": "Load",
				"Sensor": "Memory",
				"Value": 32.2,
				"measure": "%"
			},
			{
				"Hardware": "CPU",
				"Metric": "Data",
				"Sensor": "Used Memory",
				"Value": 5.1,
				"measure": "GB"
			}
		]
	},
	{
		"Language": "C",
		"time": "15",
		"data": [
			{
				"Hardware": "CPU",
				"Metric": "Temperatures",
				"Sensor": "CPU Package",
				"Value": 65,
				"measure": "°C"
			},
			{
				"Hardware": "CPU",
				"Metric": "Powers",
				"Sensor": "CPU Package",
				"Value": 7.1,
				"measure": "W"
			},
			{
				"Hardware": "CPU",
				"Metric": "Powers",
				"Sensor": "CPU Cores",
				"Value": 6.8,
				"measure": "W"
			},
			{
				"Hardware": "CPU",
				"Metric": "Load",
				"Sensor": "Memory",
				"Value": 33.1,
				"measure": "%"
			},
			{
				"Hardware": "CPU",
				"Metric": "Data",
				"Sensor": "Used Memory",
				"Value": 5.2,
				"measure": "GB"
			}
		]
	},
	{
		"Language": "C",
		"time": "16",
		"data": [
			{
				"Hardware": "CPU",
				"Metric": "Temperatures",
				"Sensor": "CPU Package",
				"Value": 64.6,
				"measure": "°C"
			},
			{
				"Hardware": "CPU",
				"Metric": "Powers",
				"Sensor": "CPU Package",
				"Value": 9.8,
				"measure": "W"
			},
			{
				"Hardware": "CPU",
				"Metric": "Powers",
				"Sensor": "CPU Cores",
				"Value": 9.3,
				"measure": "W"
			},
			{
				"Hardware": "CPU",
				"Metric": "Load",
				"Sensor": "Memory",
				"Value": 32.2,
				"measure": "%"
			},
			{
				"Hardware": "CPU",
				"Metric": "Data",
				"Sensor": "Used Memory",
				"Value": 5.1,
				"measure": "GB"
			}
		]
	},
	{
		"Language": "C",
		"time": "17",
		"data": [
			{
				"Hardware": "CPU",
				"Metric": "Temperatures",
				"Sensor": "CPU Package",
				"Value": 64.4,
				"measure": "°C"
			},
			{
				"Hardware": "CPU",
				"Metric": "Powers",
				"Sensor": "CPU Package",
				"Value": 9.6,
				"measure": "W"
			},
			{
				"Hardware": "CPU",
				"Metric": "Powers",
				"Sensor": "CPU Cores",
				"Value": 9.7,
				"measure": "W"
			},
			{
				"Hardware": "CPU",
				"Metric": "Load",
				"Sensor": "Memory",
				"Value": 32.7,
				"measure": "%"
			},
			{
				"Hardware": "CPU",
				"Metric": "Data",
				"Sensor": "Used Memory",
				"Value": 5.2,
				"measure": "GB"
			}
		]
	},
	{
		"Language": "C",
		"time": "18",
		"data": [
			{
				"Hardware": "CPU",
				"Metric": "Temperatures",
				"Sensor": "CPU Package",
				"Value": 64,
				"measure": "°C"
			},
			{
				"Hardware": "CPU",
				"Metric": "Powers",
				"Sensor": "CPU Package",
				"Value": 10.3,
				"measure": "W"
			},
			{
				"Hardware": "CPU",
				"Metric": "Powers",
				"Sensor": "CPU Cores",
				"Value": 10.8,
				"measure": "W"
			},
			{
				"Hardware": "CPU",
				"Metric": "Load",
				"Sensor": "Memory",
				"Value": 34.4,
				"measure": "%"
			},
			{
				"Hardware": "CPU",
				"Metric": "Data",
				"Sensor": "Used Memory",
				"Value": 5.5,
				"measure": "GB"
			}
		]
	}
]